sweepers/__init__.py
sweepers/cli.py
sweepers/cli_test.py
sweepers/generate.py
sweepers/generate_test.py
sweepers/run.py
sweepers/run_test.py
sweepers-0.1.0.dist-info/licenses/LICENSE
sweepers-0.1.0.dist-info/METADATA
sweepers-0.1.0.dist-info/WHEEL
sweepers-0.1.0.dist-info/entry_points.txt
sweepers-0.1.0.dist-info/top_level.txt
sweepers-0.1.0.dist-info/RECORD
