Metadata-Version: 2.4
Name: sweepers
Version: 0.1.0
Summary: CLI tool to generate parameter sweeps and run commands with the generated parameters
Requires-Python: >=3.10
License-File: LICENSE
Requires-Dist: absl-py>=2.2.2
Requires-Dist: beartype>=0.11.0
Dynamic: license-file
